task_app_micro/__init__.py
task_app_micro/todo_app.py
task_app_micro-0.1.0.dist-info/METADATA
task_app_micro-0.1.0.dist-info/WHEEL
task_app_micro-0.1.0.dist-info/licenses/LICENSE
task_app_micro-0.1.0.dist-info/RECORD
