Metadata-Version: 2.3
Name: task_app_micro
Version: 0.1.0
Summary: A small python module to create, manage and visualise Tasks and TODOs
Author: Samuel Shiels
License-File: LICENSE
Classifier: License :: OSI Approved :: MIT License
Classifier: Operating System :: POSIX :: Linux
Classifier: Programming Language :: Python :: 3
Requires-Python: >=3.11.5
